pytest_testrail/__init__.py
pytest_testrail/conftest.py
pytest_testrail/plugin.py
pytest_testrail/testrail_api.py
pytest_testrail_e2e-2.2.3.dist-info/LICENSE
pytest_testrail_e2e-2.2.3.dist-info/METADATA
pytest_testrail_e2e-2.2.3.dist-info/WHEEL
pytest_testrail_e2e-2.2.3.dist-info/entry_points.txt
pytest_testrail_e2e-2.2.3.dist-info/top_level.txt
pytest_testrail_e2e-2.2.3.dist-info/RECORD
