Metadata-Version: 2.1
Name: pytest-testrail-e2e
Version: 2.2.3
Summary: pytest plugin for creating TestRail runs and adding results
Home-page: https://github.com/vietnq254/pytest-testrail-e2e/
Author: NGUYEN Viet
Author-email: vietnq254@live.com
License: UNKNOWN
Platform: UNKNOWN
Requires-Dist: pytest (>=3.6)
Requires-Dist: requests (>=2.20.0)
